videokf/__init__.py
videokf/cli_scripts.py
videokf/extract_keyframes.py
videokf/ffmpeg_manager/__init__.py
videokf/ffmpeg_manager/check_ffmpeg.py
videokf/keyframe_manager/__init__.py
videokf/keyframe_manager/frame_manager.py
videokf/keyframe_manager/keyframe_extractor.py
videokf/utils/__init__.py
videokf/utils/all_utils.py
videokf/utils/vidutils.py
video_kf-0.0.4.dist-info/LICENSE
video_kf-0.0.4.dist-info/METADATA
video_kf-0.0.4.dist-info/WHEEL
video_kf-0.0.4.dist-info/entry_points.txt
video_kf-0.0.4.dist-info/top_level.txt
video_kf-0.0.4.dist-info/RECORD
