Metadata-Version: 2.1
Name: video-kf
Version: 0.0.4
Summary: A keyframes and ffmpeg iframes extractor
Home-page: https://github.com/averdones/video-kf
Author: Antonio Verdone
Author-email: averdones@gmail.com
Keywords: keyframes iframes video extractor
Classifier: Programming Language :: Python :: 3.6
Classifier: Programming Language :: Python :: 3.7
Classifier: License :: OSI Approved :: MIT License
Classifier: Operating System :: OS Independent
Requires-Python: >=3.6
License-File: LICENSE
Requires-Dist: numpy (>=1.17)
Requires-Dist: opencv-python (>=4)
Requires-Dist: requests (>=2.22)
